RISC-V/q2/ALUDecoder.v
module ALUDecoder (
    input [1:0] ALUOp,
    input [2:0] funct3,
    input funct7_5,
    input [6:0] opcode_5,
    output reg [2:0] ALUControl
);



always @(*) begin
    case (ALUOp)
        2'b00 : ALUControl <= 3'b000;
        2'b01 : ALUControl <= 3'b001;
        2'b10 : case({funct3})
        3'b000 : case({opcode_5[5],funct7_5})
        2'b00 : ALUControl <= 3'b000; // add
        2'b01 : ALUControl <= 3'b000; // add
        2'b10 : ALUControl <= 3'b000; // add
        2'b11 : ALUControl <= 3'b001; // sub
        default : ALUControl <= 3'bxxx;

        endcase
        
        3'b010 : ALUControl <= 3'b101; // slt
        3'b110 : ALUControl <= 3'b011; // or
        3'b111 : ALUControl <= 3'b010; // and
        3'b101 : ALUControl <= 3'b110; // sra
        endcase
    endcase
end

endmodule

RISC-V/q2/ALUDecoder_tb.v
`include "ALUDecoder.v"
module ALUDecoder_tb;

// Input signals
reg [1:0] ALUOp;
reg [2:0] funct3;
reg [6:0] funct7_5;
reg [6:0] opcode_5;

// Output signals
wire [2:0] ALUControl;

// Instantiate the ALUDecoder module
ALUDecoder uut (
    .ALUOp(ALUOp),
    .funct3(funct3),
    .funct7_5(funct7_5[5]),
    .opcode_5(opcode_5),
    .ALUControl(ALUControl)
);

// Testbench
initial begin
    $dumpfile("ALUDecoder.vcd");
    $dumpvars(0, ALUDecoder_tb);
    // Test 1: lw instructions
    ALUOp = 2'b00;

    #10;
 
    // Test 2: beq instruction
    ALUOp = 2'b01;
    #10;


    // Test 3: add instruction with opcode_5[5] = 0 and funct7_5[5] = 0
    ALUOp = 2'b10;
    funct3 = 3'b000; 
    funct7_5 = 7'b0000000; 
    opcode_5 = 7'b0000000;
    #10;
   
    
    // Test 4: sub instruction with opcode_5[5] = 1 and funct7_5[5] = 1
    ALUOp = 2'b10;
    funct3 = 3'b000;
    funct7_5 = 7'b0100000;
    opcode_5 = 7'b0110011;
    #10;

    // Test 5: slt instruction
    ALUOp = 2'b10;
    funct3 = 3'b010;
    #10;

    // Test 6: or instruction
    ALUOp = 2'b10;
    funct3 = 3'b110;

    #10;

    // Test 7: and instruction
    ALUOp = 2'b10;
    funct3 = 3'b111;

    #10;

    // Test 8: sra instruction
    ALUOp = 2'b10;
    funct3 = 3'b101;
    #10;
    $finish;
end

endmodule
//iverilog -o ALUDecoder_tb.vvp ALUDecoder_tb.v
//vvp ALUDecoder_tb.vvp
//gtkwave

RISC-V/q2/ALUDecoder.vcd
$date
	Sun Apr 28 07:09:48 2024
$end
$version
	Icarus Verilog
$end
$timescale
	1s
$end
$scope module ALUDecoder_tb $end
$var wire 3 ! ALUControl [2:0] $end
$var reg 2 " ALUOp [1:0] $end
$var reg 3 # funct3 [2:0] $end
$var reg 7 $ funct7_5 [6:0] $end
$var reg 7 % opcode_5 [6:0] $end
$scope module uut $end
$var wire 2 & ALUOp [1:0] $end
$var wire 3 ' funct3 [2:0] $end
$var wire 1 ( funct7_5 $end
$var wire 7 ) opcode_5 [6:0] $end
$var reg 3 * ALUControl [2:0] $end
$upscope $end
$upscope $end
$enddefinitions $end
$comment Show the parameter values. $end
$dumpall
$end
#0
$dumpvars
b0 *
bx )
x(
bx '
b0 &
bx %
bx $
bx #
b0 "
b0 !
$end
#10
b1 !
b1 *
b1 "
b1 &
#20
b0 !
b0 *
0(
b0 %
b0 )
b0 $
b0 #
b0 '
b10 "
b10 &
#30
b1 !
b1 *
1(
b110011 %
b110011 )
b100000 $
#40
b101 !
b101 *
b10 #
b10 '
#50
b11 !
b11 *
b110 #
b110 '
#60
b10 !
b10 *
b111 #
b111 '
#70
b110 !
b110 *
b101 #
b101 '
